exotx/__init__.py
exotx/_version.py
exotx/data/__init__.py
exotx/data/marketdata.py
exotx/data/staticdata.py
exotx/data/static/__init__.py
exotx/data/static/calendar.py
exotx/data/static/calendars.py
exotx/data/static/conventions.py
exotx/data/static/daycounters.py
exotx/enums/__init__.py
exotx/enums/enums.py
exotx/instruments/__init__.py
exotx/instruments/asian_option.py
exotx/instruments/autocallable.py
exotx/instruments/average_calculation.py
exotx/instruments/average_convention.py
exotx/instruments/average_type.py
exotx/instruments/barrier_option.py
exotx/instruments/basket_option.py
exotx/instruments/basket_type.py
exotx/instruments/instrument.py
exotx/instruments/option_type.py
exotx/instruments/vanilla_option.py
exotx/models/__init__.py
exotx/models/blackscholesmodel.py
exotx/models/hestonmodel.py
exotx/tests/__init__.py
exotx/tests/conftest.py
exotx/tests/data/__init__.py
exotx/tests/data/test_marketdata.py
exotx/tests/data/test_staticdata.py
exotx/tests/data/static/__init__.py
exotx/tests/data/static/test_calendar.py
exotx/tests/instruments/__init__.py
exotx/tests/instruments/test_asian_option.py
exotx/tests/instruments/test_autocallable_bs.py
exotx/tests/instruments/test_autocallable_heston.py
exotx/tests/instruments/test_barrier_option.py
exotx/tests/instruments/test_basket_option.py
exotx/tests/instruments/test_vanilla_option.py
exotx/tests/models/__init__.py
exotx/tests/models/test_hestonmodel.py
exotx-0.6.5.dist-info/METADATA
exotx-0.6.5.dist-info/WHEEL
exotx-0.6.5.dist-info/top_level.txt
exotx-0.6.5.dist-info/RECORD
