Metadata-Version: 2.1
Name: exotx
Version: 0.6.5
Summary: Python library for pricing autocallables
Home-page: https://github.com/SebastienEveno/exotx
Author: Sebastien Eveno
Author-email: sebastien.louis.eveno@gmail.com
License: MIT
Classifier: Development Status :: 4 - Beta
Classifier: Intended Audience :: Developers
Classifier: Intended Audience :: Financial and Insurance Industry
Classifier: License :: OSI Approved :: MIT License
Classifier: Programming Language :: Python :: 3.10
Classifier: Operating System :: OS Independent
Classifier: Intended Audience :: Science/Research
Classifier: Topic :: Software Development
Classifier: Topic :: Office/Business :: Financial
Classifier: Topic :: Scientific/Engineering :: Information Analysis
Requires-Python: >=3.10.2, <4
Requires-Dist: numpy >=1.23.5
Requires-Dist: pandas >=1.5.1
Requires-Dist: scipy >=1.9.3
Requires-Dist: matplotlib
Requires-Dist: plotly >=4.12.0
Requires-Dist: quantlib >=1.26
Requires-Dist: pytest >=7.1.3
Requires-Dist: marshmallow >=3.19.0
